setup.py
processing_spinner.egg-info/PKG-INFO
processing_spinner.egg-info/SOURCES.txt
processing_spinner.egg-info/dependency_links.txt
processing_spinner.egg-info/top_level.txt
scripts/spin
spinner/__init__.py
spinner/spinner.py