Metadata-Version: 1.1
Name: processing-spinner
Version: 0.2
Summary: Show spinner animation during processing
Home-page: https://github.com/morishin/spinner
Author: Shintaro Morikawa <sntr92@gmail.com>
Author-email: sntr92@gmail.com
License: MIT License
Platform: UNKNOWN
Classifier: Development Status :: 3 - Alpha
Classifier: Intended Audience :: Developers
Classifier: Operating System :: OS Independent
Classifier: License :: OSI Approved :: MIT License
Classifier: Programming Language :: Python
Classifier: Programming Language :: Python :: 2
Classifier: Programming Language :: Python :: 2.7
Classifier: Programming Language :: Python :: 3
Classifier: Programming Language :: Python :: 3.4
Classifier: Programming Language :: Python :: 3.5
